{"name":"Traducir de Inglés a Español","id":"traductor-de-google;traducir-de-inglés-a-español","testSteps":[{"number":1,"description":"Dado que Jose quiere usar el traductor de Google","duration":10600,"startTime":"2019-04-15T08:00:52.402-05:00[America/Bogota]","screenshots":[{"screenshot":"d5f74bc10d9779771e0301df4c15eaacf9a7e66db83a49670ed1e17f6a4b4704.png"}],"result":"SUCCESS","precondition":false,"children":[{"number":2,"description":"Jose opens the Google home page","duration":9704,"startTime":"2019-04-15T08:00:52.875-05:00[America/Bogota]","screenshots":[{"screenshot":"e8dfb25eeca7241c38baaba3c90c9ccee08000f76b88cebdedaa36dfed006dcf.png"}],"result":"SUCCESS","precondition":false}]},{"number":3,"description":"Cuando el traduce la palabra table de Inglés a Español","duration":8662,"startTime":"2019-04-15T08:01:03.002-05:00[America/Bogota]","screenshots":[{"screenshot":"c676aa64e76ba02ff4dffbd76b782115a89c59a2915f245c90dd2dc13fe23beb.png"}],"result":"SUCCESS","precondition":false,"children":[{"number":4,"description":"Jose clicks on El boton que muestra las aplicaciones","duration":529,"startTime":"2019-04-15T08:01:03.033-05:00[America/Bogota]","screenshots":[{"screenshot":"4563cb31caa635517c57c467050048b4c2a75c7fd88a05eaf8b9c5a60feaf000.png"}],"result":"SUCCESS","precondition":false},{"number":5,"description":"Jose clicks on Botón de aplicación traductor","duration":4214,"startTime":"2019-04-15T08:01:03.568-05:00[America/Bogota]","screenshots":[{"screenshot":"de67c22a30d2035ee307aae8a30f6756c65adeac01823cc8d92e7709ed51db25.png"}],"result":"SUCCESS","precondition":false},{"number":6,"description":"Jose clicks on Boton de idioma origen","duration":543,"startTime":"2019-04-15T08:01:07.787-05:00[America/Bogota]","screenshots":[{"screenshot":"316ed435445811ee918077236f6c3aeae224d8af4c9ae555dcfa80bc5369b70c.png"}],"result":"SUCCESS","precondition":false},{"number":7,"description":"Jose clicks on Seleccionar idioma de origen","duration":496,"startTime":"2019-04-15T08:01:08.334-05:00[America/Bogota]","screenshots":[{"screenshot":"11001f7312bd32145f3e8e14786614938a9a65b8713c22bb2708eb6b74c0ed8b.png"}],"result":"SUCCESS","precondition":false},{"number":8,"description":"Jose clicks on Boton idioma destino","duration":445,"startTime":"2019-04-15T08:01:08.832-05:00[America/Bogota]","screenshots":[{"screenshot":"7be0833ce5ea9d3a75c25083903720f34bc5df5eabf7f79a7eb85251f9ef6882.png"}],"result":"SUCCESS","precondition":false},{"number":9,"description":"Jose clicks on Seleccionar idioma de destino","duration":410,"startTime":"2019-04-15T08:01:09.281-05:00[America/Bogota]","screenshots":[{"screenshot":"17d8cd290ca0fa545a3513f3a801b5e63ec51023d88ebd8ae0cd5a95a34bde5d.png"}],"result":"SUCCESS","precondition":false},{"number":10,"description":"Jose clicks on Seleccionar el campo en donde escribir","duration":365,"startTime":"2019-04-15T08:01:09.696-05:00[America/Bogota]","screenshots":[{"screenshot":"91969acdc75b96444465018575cf858d6dd2bbe0e2f15a75476394a22a4782eb.png"}],"result":"SUCCESS","precondition":false},{"number":11,"description":"Jose enters \u0027table\u0027 into Seleccionar el campo en donde escribir","duration":534,"startTime":"2019-04-15T08:01:10.071-05:00[America/Bogota]","screenshots":[{"screenshot":"8793a9e420608dd63fba3163eb31c105f3b9d3d7b9d95bc6f526a6291157efa3.png"}],"result":"SUCCESS","precondition":false},{"number":12,"description":"Jose clicks on Area de traducción","duration":724,"startTime":"2019-04-15T08:01:10.609-05:00[America/Bogota]","screenshots":[{"screenshot":"c676aa64e76ba02ff4dffbd76b782115a89c59a2915f245c90dd2dc13fe23beb.png"}],"result":"SUCCESS","precondition":false}]},{"number":13,"description":"Entonces el debería ver la palabra mesa en la pantalla","duration":763,"startTime":"2019-04-15T08:01:11.664-05:00[America/Bogota]","screenshots":[{"screenshot":"c676aa64e76ba02ff4dffbd76b782115a89c59a2915f245c90dd2dc13fe23beb.png"}],"result":"SUCCESS","precondition":false,"children":[{"number":14,"description":"Then la respuesta should be \u0027mesa\u0027","duration":351,"startTime":"2019-04-15T08:01:11.772-05:00[America/Bogota]","screenshots":[{"screenshot":"c676aa64e76ba02ff4dffbd76b782115a89c59a2915f245c90dd2dc13fe23beb.png"}],"result":"SUCCESS","precondition":false}]}],"userStory":{"id":"traductor-de-google","storyName":"Traductor de Google","path":"src/test/resources/features/traductorGoogle.feature","narrative":"  Como usuario\n  Quiero ingresar al traductor de Google\n  Y traducir palabras entre diferentes leguajes","type":"feature"},"featureTag":{"name":"Features/Traductor de Google","type":"feature"},"title":"Traducir de Inglés a Español","tags":[{"name":"RunnerTags","type":"tag"},{"name":"Traductor de google","type":"feature"},{"name":"CasoExitoso","type":"tag"}],"startTime":"2019-04-15T08:00:51.078-05:00[America/Bogota]","duration":21435,"projectKey":"","sessionId":"4aa4b85ec515f566b179d92612ea8717","driver":"chrome","manual":false,"testSource":"Cucumber","result":"SUCCESS"}